agw/__init__.py
agw/app.py
agw/cli/__init__.py
agw/cli/cursor.py
agw/cli/jiggler.py
agw/cli/screen.py
agw/cli/util.py
agw/data.py
agw/screen.py
agw/util.py
agw/winapi.py
agw-0.4.4.dist-info/entry_points.txt
agw-0.4.4.dist-info/WHEEL
agw-0.4.4.dist-info/METADATA
agw-0.4.4.dist-info/RECORD
