Metadata-Version: 2.1
Name: agw
Version: 0.4.4
Summary: A pyautogui wrapper library for data entry macros.
Author: Mark Gemmill
Author-email: contact@markgemmill.com
Requires-Python: >=3.6,<4.0
Classifier: Programming Language :: Python :: 3
Classifier: Programming Language :: Python :: 3.6
Classifier: Programming Language :: Python :: 3.7
Classifier: Programming Language :: Python :: 3.8
Requires-Dist: Xlib (>=0.21,<0.22)
Requires-Dist: cutie (>=0.2.2,<0.3.0)
Requires-Dist: docopt (>=0.6.2,<0.7.0)
Requires-Dist: pyautogui (>=0.9.41,<0.10.0)
Requires-Dist: pyobjc-core (>=5.1,<6.0); sys_platform == "darwin"
Requires-Dist: pyobjc-framework-Quartz (>=5.1,<6.0); sys_platform == "darwin"
